APB_Square.sv
module APB_Square
#(parameter storona_a_ADDR = 4'h0,  // адрес регистра со стороной a
  parameter storona_b_ADDR = 4'h4,  // адрес регистра со стороной b
  parameter output_reg_ADDR = 4'h8) // адрес регистра, где хранится значение площади
(
    input wire PWRITE,            // сигнал, выбирающий режим записи или чтения (1 - запись, 0 - чтение)
    input wire PCLK,              // сигнал синхронизации
    input wire PSEL,              // сигнал выбора переферии 
    input wire [31:0] PADDR,      // Адрес регистра
    input wire [31:0] PWDATA,     // Данные для записи в регистр
    output reg [31:0] PRDATA = 0, // Данные, прочитанные из регистра
    input wire PENABLE,           // сигнал разрешения
    output reg PREADY = 0,        // сигнал готовности (флаг того, что всё сделано успешно)
	  input PRESET                  // сигнал сброса
);


reg  [31:0] storona_a  = 0;   // регистр для хранения стороны a
reg  [31:0] storona_b  = 0;   // регистр для хранения стороны b
reg  [31:0] output_reg = 0;   // регистр для хранения площади

always @(posedge PCLK) 
begin
    if(PRESET) // если обнаружен сигнал сброса, то обнуление сторон прямоугольника
	  begin
	    storona_a <= 0;
      storona_b <= 0;
	  end
	  
    else if (PSEL && !PWRITE && PENABLE) // Чтение из регистров 
     begin
        case(PADDR)
         storona_a_ADDR  : PRDATA <= storona_a;  // чтение по адресу регистра со стороной a
         storona_b_ADDR  : PRDATA <= storona_b;  // чтение по адресу регистра со стороной b
         output_reg_ADDR : PRDATA <= output_reg; // чтение по адресу выходного регистра
        endcase
        PREADY <= 1'd1; // поднимаем флаг заверешения операции
     end

     else if(PSEL && PWRITE && PENABLE) // запись производится только в регистры сторон прямоугольника
     begin
      case(PADDR)
         storona_a_ADDR : storona_a <= PWDATA;  // запись по адресу регистра со стороной a
         storona_b_ADDR : storona_b <= PWDATA;  // запись по адресу регистра со стороной b
      endcase
        PREADY <= 1'd1; // поднимаем флаг заверешения операции
     end
   
   if (PREADY) // сбрасываем PREADY после выполнения записи или чтения
    begin
      PREADY <= !PREADY;
    end
  end

always @(storona_a or storona_b) begin // блок реагирующий на изменение регистров со сторонами a и b

    if(PRESET)  // сброс значения output_reg по сигналу PRESET
	  begin
	    output_reg <= 0;
	  end
	  
    else begin
      output_reg <= storona_a * storona_b; // вычисление значения площади прямоугольника
    end
    
  
end

//iverilog -g2012 -o APB_Square.vvp APB_Square_tb.sv
//vvp APB_Square.vvp
endmodule

APB_master.sv
module APB_master
(
    input wire PCLK,                    // сигнал синхронизации
    input wire PWRITE_MASTER,           // сигнал, выбирающий режим записи или чтения (1 - запись, 0 - чтение)
    output reg PSEL = 0,                // сигнал выбора переферии 
    input wire [31:0] PADDR_MASTER,     // Адрес регистра
    input wire [31:0] PWDATA_MASTER,    // Данные для записи в регистр
    output reg [31:0] PRDATA_MASTER = 0,// Данные, прочитанные из слейва
    output reg PENABLE = 0,             // сигнал разрешения, формирующийся в мастер APB
    input wire PRESET,                  // сигнал сброса
    input wire PREADY,                  // сигнал готовности (флаг того, что всё сделано успешно)
    output reg [31:0] PADDR = 0,        // адрес, который мы будем передавать в слейв
    output reg [31:0] PWDATA = 0,       // данные, которые будут передаваться в слейв,
    input  wire [31:0] PRDATA,          // данные, прочтённые с слейва
    output reg PWRITE = 0               // сигнал записи или чтения на вход слейва
);

function void apb_write(input  [31:0] inp_addr, input  [31:0] inp_data); // функция записи
begin
  PSEL = 1'd1;        // поднимаем флаг выбора устройства
  PADDR = inp_addr;   // передаем адрес на входе мастера в слейв
  PWDATA = inp_data;  // передаём данные в слейв
  PWRITE = 1'd1;      // ставим сигнал записи
  PENABLE = 1'd1;     // выдаём разрешение на выполнение действий

  if(PREADY)
   begin
     PSEL = !PSEL;        // убираем сигнал psel
     PENABLE = !PENABLE; // убираем  сигнал PENABLE
   end
end
endfunction

function void apb_read(input [31:0] inp_addr); //функция чтения из слейва
begin
  if(!PREADY)
  begin
    PADDR = inp_addr; // передаем адрес на входе мастера в слейв
    PWRITE = 1'd0;
    PSEL = 1'd1;
    PENABLE = 1'd1;
  end
  
  else if(PREADY)
   begin
     PSEL = !PSEL;
     PENABLE = !PENABLE;
   end
end
endfunction

// циклы записи и чтения интерфейса APB
always @(posedge PCLK) 
begin
    if(PRESET) // если поднят сигнал сброса
    begin
      PADDR <= 32'b0;
      PWDATA <= 32'b0;
      PWRITE <= 1'b0;
      PSEL <= 1'b0;
      PENABLE <= 1'b0;
    end

    else if (!PWRITE_MASTER) // Чтение из регистров 
     begin
        apb_read(PADDR_MASTER); // вызов фунции чтения
     end
    else if (PWRITE_MASTER) // Запись в регистры
     begin
        apb_write(PADDR_MASTER, PWDATA_MASTER);
     end
  end

always @(posedge PREADY) // если pready поднялся в 1
begin
  if (!PWRITE_MASTER)     // если выбрана операция чтение
    begin
     PRDATA_MASTER <=PRDATA; // передаём данные на выход apb мастера
    end
end
endmodule

APB_Square_tb.sv
`include "APB_master.sv"
`include "APB_Square.sv"
module APB_Square_tb;



reg PCLK = 0;                   // сигнал синхронизации
reg PWRITE_MASTER = 0;          // сигнал, выбирающий режим записи или чтения (1 - запись, 0 - чтение)
wire PSEL;                      // сигнал выбора переферии
reg [31:0] PADDR_MASTER = 0;    // Адрес регистра
reg [31:0] PWDATA_MASTER = 0;   // Данные для записи в регистр
wire [31:0] PRDATA_MASTER;       // Данные, прочитанные из слейва
wire PENABLE;                    // сигнал разрешения, формирующийся в мастер APB
reg PRESET = 0;                   // сигнал сброса
wire PREADY;                      // сигнал готовности (флаг того, что всё сделано успешно)
wire [31:0] PADDR;                // адрес, который мы будем передавать в слейв
wire [31:0] PWDATA;               // данные, которые будут передаваться в слейв,
wire [31:0] PRDATA ;              // данные, прочтённые с слейва
wire PWRITE;                      // сигнал записи или чтения на вход слейва

APB_master APB_master_1 (
    .PCLK(PCLK),
    .PWRITE_MASTER(PWRITE_MASTER),
    .PSEL(PSEL),
    .PADDR_MASTER(PADDR_MASTER),
    .PWDATA_MASTER(PWDATA_MASTER),
    .PRDATA_MASTER(PRDATA_MASTER),
    .PENABLE(PENABLE),
    .PRESET(PRESET),
    .PREADY(PREADY),
    .PADDR(PADDR),
    .PWDATA(PWDATA),
    .PRDATA(PRDATA),
    .PWRITE(PWRITE)
);

APB_Square APB_Square_1 (
    .PWRITE(PWRITE),
    .PSEL(PSEL),
    .PADDR(PADDR),
    .PWDATA(PWDATA),
    .PRDATA(PRDATA),
    .PENABLE(PENABLE),
    .PREADY(PREADY),
    .PCLK(PCLK),
    .PRESET(PRESET)
);



always #200 PCLK = ~PCLK; // генерация входного сигнала Pclk

initial begin
    
PCLK = 0;
@(posedge PCLK);

PWRITE_MASTER = 1;           // выбираем запись
PWDATA_MASTER = 32'd5;       // записываем 5
PADDR_MASTER = 0;            // выбираем адрес регистра со стороной a
@(posedge PCLK);
@(posedge PCLK);

PWRITE_MASTER = 1;           // выбираем запись
PWDATA_MASTER = 32'd7;       // записываем 7
PADDR_MASTER = 4;            // выбираем адрес регистра со стороной a
@(posedge PCLK);
@(posedge PCLK);


PWRITE_MASTER = 1;           // выбираем запись
PWDATA_MASTER = 32'd3;       // записываем 9
PADDR_MASTER = 0;            // выбираем адрес регистра со стороной a
@(posedge PCLK);
@(posedge PCLK);

PWRITE_MASTER = 0;           // выбираем чтение
PADDR_MASTER = 0;            // выбираем адрес регистра со стороной a
@(posedge PCLK);
@(posedge PCLK);

PWRITE_MASTER = 0;           // выбираем чтение
PADDR_MASTER = 4;            // выбираем адрес регистра со стороной b
@(posedge PCLK);
@(posedge PCLK);

PWRITE_MASTER = 0;           // выбираем чтение
PADDR_MASTER = 8;            // выбираем адрес выходного регистра
@(posedge PCLK);
@(posedge PCLK);




 #500 $finish; // Заканчиваем симуляцию
end







initial begin
$dumpfile("APB_Square.vcd"); // создание файла для сохранения результатов симуляции
$dumpvars(0, APB_Square_tb); // установка переменных для сохранения в файле
$dumpvars;
end


endmodule

APB_Square.vcd
$date
	Sun Dec 24 16:53:32 2023
$end
$version
	Icarus Verilog
$end
$timescale
	1s
$end
$scope module APB_Square_tb $end
$var wire 1 ! PWRITE $end
$var wire 32 " PWDATA [31:0] $end
$var wire 1 # PSEL $end
$var wire 1 $ PREADY $end
$var wire 32 % PRDATA_MASTER [31:0] $end
$var wire 32 & PRDATA [31:0] $end
$var wire 1 ' PENABLE $end
$var wire 32 ( PADDR [31:0] $end
$var reg 32 ) PADDR_MASTER [31:0] $end
$var reg 1 * PCLK $end
$var reg 1 + PRESET $end
$var reg 32 , PWDATA_MASTER [31:0] $end
$var reg 1 - PWRITE_MASTER $end
$scope module APB_Square_1 $end
$var wire 1 * PCLK $end
$var wire 1 + PRESET $end
$var wire 1 ! PWRITE $end
$var wire 32 . PWDATA [31:0] $end
$var wire 1 # PSEL $end
$var wire 1 ' PENABLE $end
$var wire 32 / PADDR [31:0] $end
$var parameter 4 0 output_reg_ADDR $end
$var parameter 4 1 storona_a_ADDR $end
$var parameter 4 2 storona_b_ADDR $end
$var reg 32 3 PRDATA [31:0] $end
$var reg 1 $ PREADY $end
$var reg 32 4 output_reg [31:0] $end
$var reg 32 5 storona_a [31:0] $end
$var reg 32 6 storona_b [31:0] $end
$upscope $end
$scope module APB_master_1 $end
$var wire 32 7 PADDR_MASTER [31:0] $end
$var wire 1 * PCLK $end
$var wire 32 8 PRDATA [31:0] $end
$var wire 1 $ PREADY $end
$var wire 1 + PRESET $end
$var wire 32 9 PWDATA_MASTER [31:0] $end
$var wire 1 - PWRITE_MASTER $end
$var reg 32 : PADDR [31:0] $end
$var reg 1 ' PENABLE $end
$var reg 32 ; PRDATA_MASTER [31:0] $end
$var reg 1 # PSEL $end
$var reg 32 < PWDATA [31:0] $end
$var reg 1 ! PWRITE $end
$scope function apb_read $end
$var reg 32 = inp_addr [31:0] $end
$upscope $end
$scope function apb_write $end
$var reg 32 > inp_addr [31:0] $end
$var reg 32 ? inp_data [31:0] $end
$upscope $end
$upscope $end
$upscope $end
$scope module APB_Square_tb $end
$scope module APB_Square_1 $end
$upscope $end
$scope module APB_master_1 $end
$scope function apb_read $end
$upscope $end
$scope function apb_write $end
$upscope $end
$upscope $end
$upscope $end
$enddefinitions $end
$comment Show the parameter values. $end
$dumpall
b100 2
b0 1
b1000 0
$end
#0
$dumpvars
bx ?
bx >
bx =
b0 <
b0 ;
b0 :
b0 9
b0 8
b0 7
b0 6
b0 5
b0 4
b0 3
b0 /
b0 .
0-
b0 ,
0+
0*
b0 )
b0 (
0'
b0 &
b0 %
0$
0#
b0 "
0!
$end
#200
1'
1!
b101 "
b101 .
b101 <
1#
b101 ?
b0 >
b101 ,
b101 9
1-
1*
#400
0*
#600
1$
b101 5
1*
#800
0*
#1000
0$
0'
0#
b111 "
b111 .
b111 <
b100 (
b100 /
b100 :
b111 ?
b100 >
b100 )
b100 7
b111 ,
b111 9
1*
#1200
0*
#1400
b100011 4
1$
b111 6
1'
1#
1*
#1600
0*
#1800
0$
0'
0#
b11 "
b11 .
b11 <
b0 (
b0 /
b0 :
b11 ?
b0 >
b0 )
b0 7
b11 ,
b11 9
1*
#2000
0*
#2200
b10101 4
1$
b11 5
1'
1#
1*
#2400
0*
#2600
0$
0'
0#
b0 =
0-
1*
#2800
0*
#3000
b11 %
b11 ;
1$
b11 &
b11 3
b11 8
1'
1#
0!
1*
#3200
0*
#3400
0$
0'
0#
b100 =
b100 )
b100 7
1*
#3600
0*
#3800
b111 %
b111 ;
1$
b111 &
b111 3
b111 8
1'
1#
b100 (
b100 /
b100 :
1*
#4000
0*
#4200
0$
0'
0#
b1000 =
b1000 )
b1000 7
1*
#4400
0*
#4600
b10101 %
b10101 ;
1$
b10101 &
b10101 3
b10101 8
1'
1#
b1000 (
b1000 /
b1000 :
1*
#4800
0*
#5000
0$
0'
0#
1*
#5200
0*
#5400
1$
1'
1#
1*
